{
      "address": {
        "building": "123",
        "coord": [106.629664, 10.823099],
        "street": "Đường Nguyễn Huệ",
        "zipcode": "700000"
      },
      "borough": "Quận 1",
      "cuisine": "Trung Hoa",
      "grades": [
        {"date": {"$date": 1393804800000}, "grade": "A", "score": 10},
        {"date": {"$date": 1378857600000}, "grade": "A", "score": 9},
        {"date": {"$date": 1358985600000}, "grade": "A", "score": 10},
        {"date": {"$date": 1322006400000}, "grade": "A", "score": 7},
        {"date": {"$date": 1378857600000}, "grade": "B", "score": 5}
      ],
      "name": "Nhà hàng Phố Núi",
      "restaurant_id": "12345678"
    }
    {
      "address": {
        "building": "456",
        "coord": [106.629664, 10.823099],
        "street": "Đường Lê Lợi",
        "zipcode": "700000"
      },
      "borough": "Quận 1",
      "cuisine": "Nhật Bản",
      "grades": [
        {"date": {"$date": 1393804800000}, "grade": "A", "score": 10},
        {"date": {"$date": 1378857600000}, "grade": "A", "score": 8},
        {"date": {"$date": 1358985600000}, "grade": "A", "score": 8},
        {"date": {"$date": 1322006400000}, "grade": "A", "score": 9},
        {"date": {"$date": 1378857600000}, "grade": "B", "score": 6}
      ],
      "name": "Nhà hàng Sakura",
      "restaurant_id": "87654321"
    }
    
      {
        "address": {
          "building": "789",
          "coord": [106.629664, 10.823099],
          "street": "Đường Đồng Khởi",
          "zipcode": "700000"
        },
        "borough": "Quận 1",
        "cuisine": "Ý",
        "grades": [
          {"date": {"$date": 1393804800000}, "grade": "A", "score": 10},
          {"date": {"$date": 1378857600000}, "grade": "A", "score": 9},
          {"date": {"$date": 1358985600000}, "grade": "A", "score": 9},
          {"date": {"$date": 1322006400000}, "grade": "A", "score": 9},
          {"date": {"$date": 1378857600000}, "grade": "B", "score": 8}
        ],
        "name": "Nhà hàng Roma",
        "restaurant_id": "23456789"
      }
      {
        "address": {
          "building": "321",
          "coord": [106.629664, 10.823099],
          "street": "Đường Lý Tự Trọng",
          "zipcode": "700000"
        },
        "borough": "Quận 1",
        "cuisine": "Pháp",
        "grades": [
          {"date": {"$date": 1393804800000}, "grade": "A", "score": 10},
          {"date": {"$date": 1378857600000}, "grade": "A", "score": 9},
          {"date": {"$date": 1358985600000}, "grade": "A", "score": 5},
          {"date": {"$date": 1322006400000}, "grade": "A", "score": 5},
          {"date": {"$date": 1378857600000}, "grade": "B", "score": 7}
        ],
        "name": "Nhà hàng Paris",
        "restaurant_id": "98765432"
      }
      
        {
          "address": {
            "building": "160",
            "coord": [106.629664, 10.823099],
            "street": "Đường Bùi Viện",
            "zipcode": "700000"
          },
          "borough": "Quận 1",
          "cuisine": "Thái",
          "grades": [
            {"date": {"$date": 1393804800000}, "grade": "A", "score": 5},
            {"date": {"$date": 1378857600000}, "grade": "A", "score": 6},
            {"date": {"$date": 1358985600000}, "grade": "A", "score": 9},
            {"date": {"$date": 1322006400000}, "grade": "A", "score": 9},
            {"date": {"$date": 1378857600000}, "grade": "B", "score": 10}
          ],
          "name": "Nhà hàng Bangkok",
          "restaurant_id": "34567891"
        }
        {
          "address": {
            "building": "753",
            "coord": [106.629664, 10.823099],
            "street": "Đường Phạm Ngũ Lão",
            "zipcode": "700000"
          },
          "borough": "Quận 1",
          "cuisine": "Hàn Quốc",
          "grades": [
            {"date": {"$date": 1393804800000}, "grade": "A", "score": 8},
            {"date": {"$date": 1378857600000}, "grade": "A", "score": 9},
            {"date": {"$date": 1358985600000}, "grade": "A", "score": 8},
            {"date": {"$date": 1322006400000}, "grade": "A", "score": 8},
            {"date": {"$date": 1378857600000}, "grade": "B", "score": 10}
          ],
          "name": "Nhà hàng Seoul 3",
          "restaurant_id": "19876543"
        }
      
      
        {
          "address": {
            "building": "859",
            "coord": [106.629664, 10.823099],
            "street": "Đường Bùi Viện",
            "zipcode": "700000"
          },
          "borough": "Quận 1",
          "cuisine": "Thái",
          "grades": [
            {"date": {"$date": 1393804800000}, "grade": "A", "score": 10},
            {"date": {"$date": 1378857600000}, "grade": "A", "score": 10},
            {"date": {"$date": 1358985600000}, "grade": "A", "score": 10},
            {"date": {"$date": 1322006400000}, "grade": "A", "score": 9},
            {"date": {"$date": 1378857600000}, "grade": "B", "score": 9}
          ],
          "name": "Nhà hàng Bangkok 2",
          "restaurant_id": "34567891"
        }
        {
          "address": {
            "building": "553",
            "coord": [106.629664, 10.823099],
            "street": "Đường Phạm Ngũ Lão",
            "zipcode": "700000"
          },
          "borough": "Quận 1",
          "cuisine": "Hàn Quốc",
          "grades": [
            {"date": {"$date": 1393804800000}, "grade": "A", "score": 10},
            {"date": {"$date": 1378857600000}, "grade": "A", "score": 9},
            {"date": {"$date": 1358985600000}, "grade": "A", "score": 9},
            {"date": {"$date": 1322006400000}, "grade": "A", "score": 7},
            {"date": {"$date": 1378857600000}, "grade": "B", "score": 7}
          ],
          "name": "Nhà hàng Seoul 2",
          "restaurant_id": "19876543"
        }
        
          {
            "address": {
              "building": "246",
              "coord": [106.629664, 10.823099],
              "street": "Đường Bến Nghé",
              "zipcode": "700000"
            },
            "borough": "Quận 1",
            "cuisine": "Ấn Độ",
            "grades": [
              {"date": {"$date": 1393804800000}, "grade": "A", "score": 10},
              {"date": {"$date": 1378857600000}, "grade": "A", "score": 8},
              {"date": {"$date": 1358985600000}, "grade": "A", "score": 5},
              {"date": {"$date": 1322006400000}, "grade": "A", "score": 6},
              {"date": {"$date": 1378857600000}, "grade": "B", "score": 7}
            ],
            "name": "Nhà hàng Delhi",
            "restaurant_id": "45678912"
          }
          {
            "address": {
              "building": "864",
              "coord": [106.629664, 10.823099],
              "street": "Đường Hàm Nghi",
              "zipcode": "700000"
            },
            "borough": "Quận 1",
            "cuisine": "Mỹ",
            "grades": [
              {"date": {"$date": 1393804800000}, "grade": "A", "score": 10},
              {"date": {"$date": 1378857600000}, "grade": "A", "score": 8},
              {"date": {"$date": 1358985600000}, "grade": "A", "score": 8},
              {"date": {"$date": 1322006400000}, "grade": "A", "score": 9},
              {"date": {"$date": 1378857600000}, "grade": "B", "score": 8}
            ],
            "name": "Nhà hàng New York",
            "restaurant_id": "21987654"
          }
        
          
            {
              "address": {
                "building": "923",
                "coord": [106.629664, 10.823099],
                "street": "Đường Trần Hưng Đạo",
                "zipcode": "700000"
              },
              "borough": "Quận 1",
              "cuisine": "Mỹ",
              "grades": [
                {"date": {"$date": 1393804800000}, "grade": "A", "score": 10},
                {"date": {"$date": 1378857600000}, "grade": "A", "score": 9},
                {"date": {"$date": 1358985600000}, "grade": "A", "score": 10},
                {"date": {"$date": 1322006400000}, "grade": "A", "score": 9},
                {"date": {"$date": 1378857600000}, "grade": "B", "score": 10}
              ],
              "name": "Nhà hàng Texas",
              "restaurant_id": "56789123"
            }
            {
              "address": {
                "building": "356",
                "coord": [106.629664, 10.823099],
                "street": "Đường Nguyễn Thái Học",
                "zipcode": "700000"
              },
              "borough": "Quận 1",
              "cuisine": "Ý",
              "grades": [
                {"date": {"$date": 1393804800000}, "grade": "A", "score": 10},
                {"date": {"$date": 1378857600000}, "grade": "A", "score": 9},
                {"date": {"$date": 1358985600000}, "grade": "A", "score": 9},
                {"date": {"$date": 1322006400000}, "grade": "A", "score": 8},
                {"date": {"$date": 1378857600000}, "grade": "B", "score": 8}
              ],
              "name": "Nhà hàng Venice",
              "restaurant_id": "67891234"
            }
            {
              "address": {
                "building": "865",
                "coord": [106.629664, 10.823099],
                "street": "Đường Lê Lợi",
                "zipcode": "700000"
              },
              "borough": "Quận 1",
              "cuisine": "Nhật Bản",
              "grades": [
                {"date": {"$date": 1393804800000}, "grade": "A", "score": 10},
                {"date": {"$date": 1378857600000}, "grade": "A", "score": 9},
                {"date": {"$date": 1358985600000}, "grade": "A", "score": 8},
                {"date": {"$date": 1322006400000}, "grade": "A", "score": 7},
                {"date": {"$date": 1378857600000}, "grade": "B", "score": 7}
              ],
              "name": "Nhà hàng Tokyo",
              "restaurant_id": "78912345"
            }
            {
              "address": {
                "building": "159",
                "coord": [106.629664, 10.823099],
                "street": "Đường Bến Nghé",
                "zipcode": "700000"
              },
              "borough": "Quận 1",
              "cuisine": "Ấn Độ",
              "grades": [
                {"date": {"$date": 1393804800000}, "grade": "A", "score": 10},
                {"date": {"$date": 1378857600000}, "grade": "A", "score": 8},
                {"date": {"$date": 1358985600000}, "grade": "A", "score": 8},
                {"date": {"$date": 1322006400000}, "grade": "A", "score": 5},
                {"date": {"$date": 1378857600000}, "grade": "B", "score": 5}
              ],
              "name": "Nhà hàng Mumbai",
              "restaurant_id": "89123456"
            }
            {
              "address": {
                "building": "253",
                "coord": [106.629664, 10.823099],
                "street": "Đường Phạm Ngũ Lão",
                "zipcode": "700000"
              },
              "borough": "Quận 1",
              "cuisine": "Hàn Quốc",
              "grades": [
                {"date": {"$date": 1393804800000}, "grade": "A", "score": 10},
                {"date": {"$date": 1378857600000}, "grade": "A", "score": 9},
                {"date": {"$date": 1358985600000}, "grade": "A", "score": 8},
                {"date": {"$date": 1322006400000}, "grade": "A", "score": 6},
                {"date": {"$date": 1378857600000}, "grade": "B", "score": 6}
              ],
              "name": "Nhà hàng Seoul 1",
              "restaurant_id": "91234567"
            }
          
            
              {
                "address": {
                  "building": "951",
                  "coord": [106.629664, 10.823099],
                  "street": "Đường Nguyễn Văn Cừ",
                  "zipcode": "700000"
                },
                "borough": "Quận 5",
                "cuisine": "Việt Nam",
                "grades": [
                  {"date": {"$date": 1393804800000}, "grade": "A", "score": 10},
                  {"date": {"$date": 1378857600000}, "grade": "A", "score": 9},
                  {"date": {"$date": 1358985600000}, "grade": "A", "score": 8},
                  {"date": {"$date": 1322006400000}, "grade": "A", "score": 7},
                  {"date": {"$date": 1378857600000}, "grade": "B", "score": 6}
                ],
                "name": "Nhà hàng Sông Hương",
                "restaurant_id": "56789123"
              }
              {
                "address": {
                  "building": "357",
                  "coord": [106.629664, 10.823099],
                  "street": "Đường Trần Hưng Đạo",
                  "zipcode": "700000"
                },
                "borough": "Quận 5",
                "cuisine": "Trung Hoa",
                "grades": [
                  {"date": {"$date": 1393804800000}, "grade": "A", "score": 10},
                  {"date": {"$date": 1378857600000}, "grade": "A", "score": 9},
                  {"date": {"$date": 1358985600000}, "grade": "A", "score": 8},
                  {"date": {"$date": 1322006400000}, "grade": "A", "score": 7},
                  {"date": {"$date": 1378857600000}, "grade": "B", "score": 6}
                ],
                "name": "Nhà hàng Đại Tái",
                "restaurant_id": "67891234"
              }
              {
                "address": {
                  "building": "888",
                  "coord": [106.629664, 10.823099],
                  "street": "Đường Nguyễn Trãi",
                  "zipcode": "700000"
                },
                "borough": "Quận 5",
                "cuisine": "Nhật Bản",
                "grades": [
                  {"date": {"$date": 1393804800000}, "grade": "A", "score": 10},
                  {"date": {"$date": 1378857600000}, "grade": "A", "score": 9},
                  {"date": {"$date": 1358985600000}, "grade": "A", "score": 8},
                  {"date": {"$date": 1322006400000}, "grade": "A", "score": 7},
                  {"date": {"$date": 1378857600000}, "grade": "B", "score": 6}
                ],
                "name": "Nhà hàng Tokyo chi nhánh 2",
                "restaurant_id": "78912345"
              }
              {
                "address": {
                  "building": "122",
                  "coord": [106.629664, 10.823099],
                  "street": "Đường An Dương Vương",
                  "zipcode": "700000"
                },
                "borough": "Quận 5",
                "cuisine": "Ấn Độ",
                "grades": [
                  {"date": {"$date": 1393804800000}, "grade": "A", "score": 10},
                  {"date": {"$date": 1378857600000}, "grade": "A", "score": 9},
                  {"date": {"$date": 1358985600000}, "grade": "A", "score": 8},
                  {"date": {"$date": 1322006400000}, "grade": "A", "score": 7},
                  {"date": {"$date": 1378857600000}, "grade": "B", "score": 6}
                ],
                "name": "Nhà hàng Mumbai",
                "restaurant_id": "89123456"
              }

              
                {
                  "address": {
                    "building": "250",
                    "coord": [106.629664, 10.823099],
                    "street": "Đường Nguyễn Văn Linh",
                    "zipcode": "700000"
                  },
                  "borough": "Quận 7",
                  "cuisine": "Mỹ",
                  "grades": [
                    {"date": {"$date": 1393804800000}, "grade": "A", "score": 7},
                    {"date": {"$date": 1378857600000}, "grade": "A", "score": 9},
                    {"date": {"$date": 1358985600000}, "grade": "A", "score": 8},
                    {"date": {"$date": 1322006400000}, "grade": "A", "score": 6},
                    {"date": {"$date": 1378857600000}, "grade": "B", "score": 5}
                  ],
                  "name": "Nhà hàng Mississippi",
                  "restaurant_id": "56789123"
                }
                {
                  "address": {
                    "building": "355",
                    "coord": [106.629664, 10.823099],
                    "street": "Đường Lê Văn Sỹ",
                    "zipcode": "700000"
                  },
                  "borough": "Quận 3",
                  "cuisine": "Ý",
                  "grades": [
                    {"date": {"$date": 1393804800000}, "grade": "A", "score": 10},
                    {"date": {"$date": 1378857600000}, "grade": "A", "score": 8},
                    {"date": {"$date": 1358985600000}, "grade": "A", "score": 6},
                    {"date": {"$date": 1322006400000}, "grade": "A", "score": 7},
                    {"date": {"$date": 1378857600000}, "grade": "B", "score": 9}
                  ],
                  "name": "Nhà hàng Roma Deli",
                  "restaurant_id": "67891234"
                }
                {
                  "address": {
                    "building": "850",
                    "coord": [106.629664, 10.823099],
                    "street": "Đường Cách Mạng Tháng Tám",
                    "zipcode": "700000"
                  },
                  "borough": "Quận 3",
                  "cuisine": "Nhật Bản",
                  "grades": [
                    {"date": {"$date": 1393804800000}, "grade": "A", "score": 9},
                    {"date": {"$date": 1378857600000}, "grade": "A", "score": 7},
                    {"date": {"$date": 1358985600000}, "grade": "A", "score": 10},
                    {"date": {"$date": 1322006400000}, "grade": "A", "score": 8},
                    {"date": {"$date": 1378857600000}, "grade": "B", "score": 6}
                  ],
                  "name": "Nhà hàng Osaka",
                  "restaurant_id": "78912345"
                }
                {
                  "address": {
                    "building": "162",
                    "coord": [106.629664, 10.823099],
                    "street": "Đường Trường Sa",
                    "zipcode": "700000"
                  },
                  "borough": "Quận Phú Nhuận",
                  "cuisine": "Ấn Độ",
                  "grades": [
                    {"date": {"$date": 1393804800000}, "grade": "A", "score": 6},
                    {"date": {"$date": 1378857600000}, "grade": "A", "score": 8},
                    {"date": {"$date": 1358985600000}, "grade": "A", "score": 7},
                    {"date": {"$date": 1322006400000}, "grade": "A", "score": 10},
                    {"date": {"$date": 1378857600000}, "grade": "B", "score": 9}
                  ],
                  "name": "Nhà hàng Delhi Palace",
                  "restaurant_id": "89123456"
                }
                {
                  "address": {
                    "building": "755",
                    "coord": [106.629664, 10.823099],
                    "street": "Đường Nguyễn Đình Chiểu",
                    "zipcode": "700000"
                  },
                  "borough": "Quận 3",
                  "cuisine": "Hàn Quốc",
                  "grades": [
                    {"date": {"$date": 1393804800000}, "grade": "A", "score": 5},
                    {"date": {"$date": 1378857600000}, "grade": "A", "score": 7},
                    {"date": {"$date": 1358985600000}, "grade": "A", "score": 9},
                    {"date": {"$date": 1322006400000}, "grade": "A", "score": 8},
                    {"date": {"$date": 1378857600000}, "grade": "B", "score": 10}
                  ],
                  "name": "Nhà hàng Seoul Garden",
                  "restaurant_id": "91234567"
                }
                {
                  "address": {
                    "building": "777",
                    "coord": [106.629664, 10.823099],
                    "street": "Đường Lê Lai",
                    "zipcode": "700000"
                  },
                  "borough": "Quận 1",
                  "cuisine": "Đa dạng",
                  "grades": [
                    {"date": {"$date": 1393804800000}, "grade": "A", "score": 9},
                    {"date": {"$date": 1378857600000}, "grade": "A", "score": 9},
                    {"date": {"$date": 1358985600000}, "grade": "A", "score": 9}
                  ],
                  "name": "Nhà hàng Lê Lai ",
                  "restaurant_id": "77777777"
                }
                
                {
                  "address": {
                    "building": "5A Tống Hữu Định",
                    "coord": [106.629664, 10.823099],
                    "street": "Đường Phạm Ngũ Lão",
                    "zipcode": "700000"
                  },
                  "borough": "Thủ Đức",
                  "cuisine": "Việt Nam",
                  "grades": [
                    {"date": {"$date": 1393804800000}, "grade": "A", "score": 10},
                    {"date": {"$date": 1378857600000}, "grade": "A", "score": 9},
                    {"date": {"$date": 1358985600000}, "grade": "A", "score": 9},
                    {"date": {"$date": 1322006400000}, "grade": "A", "score": 8},
                    {"date": {"$date": 1378857600000}, "grade": "B", "score": 9}
                  ],
                  "name": "An’s Sài Gòn",
                  "restaurant_id": "12345678"
                }
                
                  {
                    "address": {
                      "building": "39",
                      "coord": [106.629664, 10.823099],
                      "street": "Đường Trần Ngọc Diện",
                      "zipcode": "700000"
                    },
                    "borough": "Quận 2",
                    "cuisine": "Đa dạng",
                    "grades": [
                      {"date": {"$date": 1393804800000}, "grade": "A", "score": 7},
                      {"date": {"$date": 1378857600000}, "grade": "A", "score": 9},
                      {"date": {"$date": 1358985600000}, "grade": "A", "score": 8},
                      {"date": {"$date": 1322006400000}, "grade": "A", "score": 6},
                      {"date": {"$date": 1378857600000}, "grade": "B", "score": 5}
                    ],
                    "name": "3G Trols Gourmands",
                    "restaurant_id": "56789123"
                  }

                  {
                    "address": {
                      "building": "31-33",
                      "coord": [106.629664, 10.823099],
                      "street": "Đặng Dung",
                      "zipcode": "700000"
                    },
                    "borough": "Quận 1",
                    "cuisine": "Đa dạng",
                    "grades": [
                      {"date": {"$date": 1393804800000}, "grade": "A", "score": 10},
                      {"date": {"$date": 1378857600000}, "grade": "A", "score": 8},
                      {"date": {"$date": 1358985600000}, "grade": "A", "score": 6},
                      {"date": {"$date": 1322006400000}, "grade": "A", "score": 7},
                      {"date": {"$date": 1378857600000}, "grade": "B", "score": 9}
                    ],
                    "name": "A by T.U.N.G",
                    "restaurant_id": "67891234"
                  }
        
                  {
                      "address": {
                        "building": "55 - 57",
                        "coord": [106.629664, 10.823099],
                        "street": "Nguyễn Huệ",
                        "zipcode": "700000"
                      },
                      "borough": "Quận 1",
                      "cuisine": "Chưa xác định",
                      "grades": [
                        {"date": {"$date": 1393804800000}, "grade": "A", "score": 7},
                        {"date": {"$date": 1378857600000}, "grade": "A", "score": 9},
                        {"date": {"$date": 1358985600000}, "grade": "A", "score": 8},
                        {"date": {"$date": 1322006400000}, "grade": "A", "score": 6},
                        {"date": {"$date": 1378857600000}, "grade": "B", "score": 5}
                      ],
                      "name": "Amigo",
                      "restaurant_id": "56789123"
                  }
                  {
                      "address": {
                        "building": "16",
                        "coord": [106.629664, 10.823099],
                        "street": "Cao Bá Quát",
                        "zipcode": "700000"
                      },
                      "borough": "Quận 1",
                      "cuisine": "Pháp",
                      "grades": [
                        {"date": {"$date": 1393804800000}, "grade": "A", "score": 10},
                        {"date": {"$date": 1378857600000}, "grade": "A", "score": 8},
                        {"date": {"$date": 1358985600000}, "grade": "A", "score": 6},
                        {"date": {"$date": 1322006400000}, "grade": "A", "score": 7},
                        {"date": {"$date": 1378857600000}, "grade": "B", "score": 9}
                      ],
                      "name": "Camargue",
                      "restaurant_id": "67891234"
                  }
                  {
                      "address": {
                        "building": "160B",
                        "coord": [106.629664, 10.823099],
                        "street": "Trần Hưng Đạo",
                        "zipcode": "700000"
                      },
                      "borough": "Quận 1",
                      "cuisine": "Á, Âu",
                      "grades": [
                        {"date": {"$date": 1393804800000}, "grade": "A", "score": 9},
                        {"date": {"$date": 1378857600000}, "grade": "A", "score": 7},
                        {"date": {"$date": 1358985600000}, "grade": "A", "score": 10},
                        {"date": {"$date": 1322006400000}, "grade": "A", "score": 8},
                        {"date": {"$date": 1378857600000}, "grade": "B", "score": 6}
                      ],
                      "name": "Château",
                      "restaurant_id": "78912345"
                  }

                  {
                      "address": {
                        "building": "34",
                        "coord": [106.629664, 10.823099],
                        "street": "Đồng Khởi",
                        "zipcode": "700000"
                      },
                      "borough": "Quận 1",
                      "cuisine": "Đức",
                      "grades": [
                        {"date": {"$date": 1393804800000}, "grade": "A", "score": 9},
                        {"date": {"$date": 1378857600000}, "grade": "A", "score": 7},
                        {"date": {"$date": 1358985600000}, "grade": "A", "score": 8},
                        {"date": {"$date": 1322006400000}, "grade": "A", "score": 8},
                        {"date": {"$date": 1378857600000}, "grade": "B", "score": 6}
                      ],
                      "name": "Garten Stadt",
                      "restaurant_id": "78912345"
                  }
                          
                  {
                    "address": {
                      "building": "197",
                      "coord": [106.629664, 10.823099],
                      "street": "Đề Thám",
                      "zipcode": "700000"
                    },
                    "borough": "Quận 1",
                    "cuisine": "Ý",
                    "grades": [
                      {"date": {"$date": 1393804800000}, "grade": "A", "score": 10},
                      {"date": {"$date": 1378857600000}, "grade": "A", "score": 8},
                      {"date": {"$date": 1358985600000}, "grade": "A", "score": 6},
                      {"date": {"$date": 1322006400000}, "grade": "A", "score": 7},
                      {"date": {"$date": 1378857600000}, "grade": "B", "score": 9}
                    ],
                    "name": "Good morning Vietnam",
                    "restaurant_id": "67891234"
                  }

                  {
                    "address": {
                      "building": "76",
                      "coord": [106.629664, 10.823099],
                      "street": "Sương Nguyệt Ánh",
                      "zipcode": "700000"
                    },
                    "borough": "Quận 1",
                    "cuisine": "Việt,Pháp",
                    "grades": [
                      {"date": {"$date": 1393804800000}, "grade": "A", "score": 9},
                      {"date": {"$date": 1378857600000}, "grade": "A", "score": 7},
                      {"date": {"$date": 1358985600000}, "grade": "A", "score": 10},
                      {"date": {"$date": 1322006400000}, "grade": "A", "score": 8},
                      {"date": {"$date": 1378857600000}, "grade": "B", "score": 6}
                    ],
                    "name": "La Taverne",
                    "restaurant_id": "78912345"
                  }
                  
                    {
                      "address": {
                        "building": "F7 - F8",
                        "coord": [106.629664, 10.823099],
                        "street": "D2 Văn Thánh",
                        "zipcode": "700000"
                      },
                      "borough": "Quận Bình Thạnh",
                      "cuisine": "Đa dạng",
                      "grades": [
                        {"date": {"$date": 1393804800000}, "grade": "A", "score": 7},
                        {"date": {"$date": 1378857600000}, "grade": "A", "score": 9},
                        {"date": {"$date": 1358985600000}, "grade": "A", "score": 8},
                        {"date": {"$date": 1322006400000}, "grade": "A", "score": 6},
                        {"date": {"$date": 1378857600000}, "grade": "B", "score": 5}
                      ],
                      "name": "Le Bordeaux",
                      "restaurant_id": "56789123"
                    }

                    {
                      "address": {
                        "building": "35",
                        "coord": [106.629664, 10.823099],
                        "street": "Đông Du",
                        "zipcode": "700000"
                      },
                      "borough": "Quận 1",
                      "cuisine": "Pháp",
                      "grades": [
                        {"date": {"$date": 1393804800000}, "grade": "A", "score": 10},
                        {"date": {"$date": 1378857600000}, "grade": "A", "score": 8},
                        {"date": {"$date": 1358985600000}, "grade": "A", "score": 6},
                        {"date": {"$date": 1322006400000}, "grade": "A", "score": 7},
                        {"date": {"$date": 1378857600000}, "grade": "B", "score": 9}
                      ],
                      "name": "Sama",
                      "restaurant_id": "67891234"
                    }
                    {
                      "address": {
                        "building": "215C",
                        "coord": [106.629664, 10.823099],
                        "street": "Lý Thường Kiệt",
                        "zipcode": "700000"
                      },
                      "borough": "Quận 11",
                      "cuisine": "Đa dạng",
                      "grades": [
                        {"date": {"$date": 1393804800000}, "grade": "A", "score": 9},
                        {"date": {"$date": 1378857600000}, "grade": "A", "score": 7},
                        {"date": {"$date": 1358985600000}, "grade": "A", "score": 10},
                        {"date": {"$date": 1322006400000}, "grade": "A", "score": 8},
                        {"date": {"$date": 1378857600000}, "grade": "B", "score": 6}
                      ],
                      "name": "Phong Lan",
                      "restaurant_id": "78912345"
                    }
                  
                      {
                        "address": {
                          "building": "3",
                          "coord": [106.629664, 10.823099],
                          "street": "Hoà Bình",
                          "zipcode": "700000"
                        },
                        "borough": "Quận 11",
                        "cuisine": "Đa dạng",
                        "grades": [
                          {"date": {"$date": 1393804800000}, "grade": "A", "score": 7},
                          {"date": {"$date": 1378857600000}, "grade": "A", "score": 9},
                          {"date": {"$date": 1358985600000}, "grade": "A", "score": 8},
                          {"date": {"$date": 1322006400000}, "grade": "A", "score": 6},
                          {"date": {"$date": 1378857600000}, "grade": "B", "score": 5}
                        ],
                        "name": "Thủy Tạ Đầm Sen",
                        "restaurant_id": "56789123"
                      }
                      {
                        "address": {
                          "building": "17",
                          "coord": [106.629664, 10.823099],
                          "street": "Hoàng Việt",
                          "zipcode": "700000"
                        },
                        "borough": "Quận Tân Bình",
                        "cuisine": "Hàn Quốc",
                        "grades": [
                          {"date": {"$date": 1393804800000}, "grade": "A", "score": 10},
                          {"date": {"$date": 1378857600000}, "grade": "A", "score": 8},
                          {"date": {"$date": 1358985600000}, "grade": "A", "score": 6},
                          {"date": {"$date": 1322006400000}, "grade": "A", "score": 7},
                          {"date": {"$date": 1378857600000}, "grade": "B", "score": 9}
                        ],
                        "name": "Arirang KaTun",
                        "restaurant_id": "67891234"
                      }
                      
                      {
                        "address": {
                          "building": "17/10",
                          "coord": [106.629664, 10.823099],
                          "street": "Lê Thánh Tôn",
                          "zipcode": "700000"
                        },
                        "borough": "Quận 1",
                        "cuisine": "Ấn Độ",
                        "grades": [
                          {"date": {"$date": 1393804800000}, "grade": "A", "score": 9},
                          {"date": {"$date": 1378857600000}, "grade": "A", "score": 7},
                          {"date": {"$date": 1358985600000}, "grade": "A", "score": 10},
                          {"date": {"$date": 1322006400000}, "grade": "A", "score": 8},
                          {"date": {"$date": 1378857600000}, "grade": "B", "score": 6}
                        ],
                        "name": "Ashoka",
                        "restaurant_id": "78912345"
                      }

                      {
                        "address": {
                          "building": "77-89",
                          "coord": [106.629664, 10.823099],
                          "street": "Nam Kỳ Khởi Nghĩa",
                          "zipcode": "700000"
                        },
                        "borough": "Quận 1",
                        "cuisine": "Đa dạng",
                        "grades": [
                          {"date": {"$date": 1393804800000}, "grade": "A", "score": 5},
                          {"date": {"$date": 1378857600000}, "grade": "A", "score": 7},
                          {"date": {"$date": 1358985600000}, "grade": "A", "score": 9},
                          {"date": {"$date": 1322006400000}, "grade": "A", "score": 8},
                          {"date": {"$date": 1378857600000}, "grade": "B", "score": 10}
                        ],
                        "name": "HiSago",
                        "restaurant_id": "89123456"
                      }
                    
                      {
                        "address": {
                          "building": "A43",
                          "coord": [106.629664, 10.823099],
                          "street": "Trường Sơn",
                          "zipcode": "700000"
                        },
                        "borough": "Quận Tân Bình",
                        "cuisine": "Philippines",
                        "grades": [
                          {"date": {"$date": 1393804800000}, "grade": "A", "score": 5},
                          {"date": {"$date": 1378857600000}, "grade": "A", "score": 8},
                          {"date": {"$date": 1358985600000}, "grade": "A", "score": 9},
                          {"date": {"$date": 1322006400000}, "grade": "A", "score": 8},
                          {"date": {"$date": 1378857600000}, "grade": "B", "score": 10}
                        ],
                        "name": "Jollibee",
                        "restaurant_id": "59123456"
                      }           
                                          
                      {
                        "address": {
                          "building": "37",
                          "coord": [106.629664, 10.823099],
                          "street": "Đông Du",
                          "zipcode": "700000"
                        },
                        "borough": "Quận 1",
                        "cuisine": "Thái",
                        "grades": [
                          {"date": {"$date": 1393804800000}, "grade": "A", "score": 10},
                          {"date": {"$date": 1378857600000}, "grade": "A", "score": 8},
                          {"date": {"$date": 1358985600000}, "grade": "A", "score": 6},
                          {"date": {"$date": 1322006400000}, "grade": "A", "score": 7},
                          {"date": {"$date": 1378857600000}, "grade": "B", "score": 9}
                        ],
                        "name": "Malee Thái",
                        "restaurant_id": "67891234"
                      }

                      {
                        "address": {
                          "building": "22-36",
                          "coord": [106.629664, 10.823099],
                          "street": "Nguyễn Huệ",
                          "zipcode": "700000"
                        },
                        "borough": "Quận 1",
                        "cuisine": "Việt Nam, Hồng Kông, Trung Quốc, Thái Lan",
                        "grades": [
                          {"date": {"$date": 1393804800000}, "grade": "A", "score": 9},
                          {"date": {"$date": 1378857600000}, "grade": "A", "score": 7},
                          {"date": {"$date": 1358985600000}, "grade": "A", "score": 10},
                          {"date": {"$date": 1322006400000}, "grade": "A", "score": 8},
                          {"date": {"$date": 1378857600000}, "grade": "B", "score": 6}
                        ],
                        "name": "Ngân Đình",
                        "restaurant_id": "78912345"
                      }

                      {
                        "address": {
                          "building": "111",
                          "coord": [106.629664, 10.823099],
                          "street": "Hai Bà Trưng",
                          "zipcode": "700000"
                        },
                        "borough": "Quận 1",
                        "cuisine": "Đa dạng",
                        "grades": [
                          {"date": {"$date": 1393804800000}, "grade": "A", "score": 5},
                          {"date": {"$date": 1378857600000}, "grade": "A", "score": 7},
                          {"date": {"$date": 1358985600000}, "grade": "A", "score": 9},
                          {"date": {"$date": 1322006400000}, "grade": "A", "score": 8},
                          {"date": {"$date": 1378857600000}, "grade": "B", "score": 10}
                        ],
                        "name": "Sarangbang",
                        "restaurant_id": "89123456"
                      }

                      {
                        "address": {
                          "building": "5",
                          "coord": [106.629664, 10.823099],
                          "street": "Công Trường Mê Linh",
                          "zipcode": "700000"
                        },
                        "borough": "Quận 1",
                        "cuisine": "Đa dạng",
                        "grades": [
                          {"date": {"$date": 1393804800000}, "grade": "A", "score": 6},
                          {"date": {"$date": 1378857600000}, "grade": "A", "score": 8},
                          {"date": {"$date": 1358985600000}, "grade": "A", "score": 7},
                          {"date": {"$date": 1322006400000}, "grade": "A", "score": 10},
                          {"date": {"$date": 1378857600000}, "grade": "B", "score": 9}
                        ],
                        "name": "Yeebo",
                        "restaurant_id": "91234567"
                      }
                      
                        {
                          "address": {
                            "building": "88",
                            "coord": [106.629664, 10.823099],
                            "street": "Nguyễn Du",
                            "zipcode": "700000"
                          },
                          "borough": "Quận 1",
                          "cuisine": "Đa dạng",
                          "grades": [
                            {"date": {"$date": 1393804800000}, "grade": "A", "score": 7},
                            {"date": {"$date": 1378857600000}, "grade": "A", "score": 9},
                            {"date": {"$date": 1358985600000}, "grade": "A", "score": 8},
                            {"date": {"$date": 1322006400000}, "grade": "A", "score": 6},
                            {"date": {"$date": 1378857600000}, "grade": "B", "score": 5}
                          ],
                          "name": "Cơm Ngon",
                          "restaurant_id": "56789123"
                        }
                        {
                          "address": {
                            "building": "146",
                            "coord": [106.629664, 10.823099],
                            "street": "Pasteur",
                            "zipcode": "700000"
                          },
                          "borough": "Quận 1",
                          "cuisine": "Đa dạng",
                          "grades": [
                            {"date": {"$date": 1393804800000}, "grade": "A", "score": 10},
                            {"date": {"$date": 1378857600000}, "grade": "A", "score": 8},
                            {"date": {"$date": 1358985600000}, "grade": "A", "score": 6},
                            {"date": {"$date": 1322006400000}, "grade": "A", "score": 7},
                            {"date": {"$date": 1378857600000}, "grade": "B", "score": 9}
                          ],
                          "name": "Cung Đình Rex",
                          "restaurant_id": "67891234"
                        }

                        {
                          "address": {
                            "building": "30",
                            "coord": [106.629664, 10.823099],
                            "street": "Đồng Khởi",
                            "zipcode": "700000"
                          },
                          "borough": "Quận 1",
                          "cuisine": "Đa dạng",
                          "grades": [
                            {"date": {"$date": 1393804800000}, "grade": "A", "score": 9},
                            {"date": {"$date": 1378857600000}, "grade": "A", "score": 7},
                            {"date": {"$date": 1358985600000}, "grade": "A", "score": 10},
                            {"date": {"$date": 1322006400000}, "grade": "A", "score": 8},
                            {"date": {"$date": 1378857600000}, "grade": "B", "score": 6}
                          ],
                          "name": "Kinh Bắc",
                          "restaurant_id": "78912345"
                        }
                        {
                          "address": {
                            "building": "80",
                            "coord": [106.629664, 10.823099],
                            "street": "Đồng Khởi",
                            "zipcode": "700000"
                          },
                          "borough": "Quận 1",
                          "cuisine": "Đa dạng",
                          "grades": [
                            {"date": {"$date": 1393804800000}, "grade": "A", "score": 5},
                            {"date": {"$date": 1378857600000}, "grade": "A", "score": 7},
                            {"date": {"$date": 1358985600000}, "grade": "A", "score": 9},
                            {"date": {"$date": 1322006400000}, "grade": "A", "score": 8},
                            {"date": {"$date": 1378857600000}, "grade": "B", "score": 10}
                          ],
                          "name": "Liberty",
                          "restaurant_id": "89123456"
                        }
                        {
                          "address": {
                            "building": "64",
                            "coord": [106.629664, 10.823099],
                            "street": "Lê Thánh Tôn",
                            "zipcode": "700000"
                          },
                          "borough": "Quận 1",
                          "cuisine": "Đa dạng",
                          "grades": [
                            {"date": {"$date": 1393804800000}, "grade": "A", "score": 5},
                            {"date": {"$date": 1378857600000}, "grade": "A", "score": 7},
                            {"date": {"$date": 1358985600000}, "grade": "A", "score": 9},
                            {"date": {"$date": 1322006400000}, "grade": "A", "score": 8},
                            {"date": {"$date": 1378857600000}, "grade": "B", "score": 10}
                          ],
                          "name": "Nam Phan",
                          "restaurant_id": "91234567"
                        }
                      
                      
                                                      